dupdetsdk/__init__.py
dupdetsdk/dataset_observer.py
dupdetsdk/dataset_pacer.py
dupdetsdk/feature_model.py
dupdetsdk/rule_model.py
dupdetsdk/utils.py
dupdetsdk-0.3.1.dist-info/licenses/LICENSE
dupdetsdk-0.3.1.dist-info/METADATA
dupdetsdk-0.3.1.dist-info/WHEEL
dupdetsdk-0.3.1.dist-info/top_level.txt
dupdetsdk-0.3.1.dist-info/RECORD
