Metadata-Version: 2.4
Name: dupdetsdk
Version: 0.3.1
Summary: A package for detecting content duplication
Home-page: https://github.com/yourusername/dupdetsdk
Author: Junzhi Cai
Author-email: junzhi.cai@anker-in.com
License: MIT
Project-URL: Bug Tracker, https://github.com/yourusername/dupdetsdk/issues
Classifier: Programming Language :: Python :: 3
Classifier: Operating System :: OS Independent
Requires-Python: >=3.9
License-File: LICENSE
Requires-Dist: chromadb>=0.5.5
Requires-Dist: dataloopsdk
Requires-Dist: loguru>=0.7.0
Requires-Dist: numpy
Requires-Dist: Pillow
Requires-Dist: torch<2.5.0,>=2.4.0
Requires-Dist: torchvision<0.20.0,>=0.19.0
Requires-Dist: tokenizers>=0.13.0
Dynamic: author
Dynamic: author-email
Dynamic: classifier
Dynamic: description
Dynamic: description-content-type
Dynamic: home-page
Dynamic: license
Dynamic: license-file
Dynamic: project-url
Dynamic: requires-dist
Dynamic: requires-python
Dynamic: summary
